{
  "version": "7",
  "dialect": "postgresql",
  "entries": [
    {
      "idx": 0,
      "version": "7",
      "when": 1778413015941,
      "tag": "0000_short_miek",
      "breakpoints": true
    },
    {
      "idx": 1,
      "version": "7",
      "when": 1778417717058,
      "tag": "0001_strange_romulus",
      "breakpoints": true
    },
    {
      "idx": 2,
      "version": "7",
      "when": 1778476404549,
      "tag": "0002_abandoned_silver_sable",
      "breakpoints": true
    },
    {
      "idx": 3,
      "version": "7",
      "when": 1778481126819,
      "tag": "0003_whole_tempest",
      "breakpoints": true
    },
    {
      "idx": 4,
      "version": "7",
      "when": 1778586542392,
      "tag": "0004_romantic_maverick",
      "breakpoints": true
    },
    {
      "idx": 5,
      "version": "7",
      "when": 1778596783223,
      "tag": "0005_sleepy_jimmy_woo",
      "breakpoints": true
    },
    {
      "idx": 6,
      "version": "7",
      "when": 1778654225288,
      "tag": "0006_mysterious_puma",
      "breakpoints": true
    }
  ]
}